<key>cascading-variable</key>
<dict>
	<key>begin</key>
	<string>(var)\s*(\()</string>
	<key>beginCaptures</key>
	<dict>
		<key>1</key>
		<dict>
			<key>name</key>
			<string>support.function.var.css</string>
		</dict>
		<key>2</key>
		<dict>
			<key>name</key>
			<string>punctuation.section.function.css</string>
		</dict>
	</dict>
	<key>patterns</key>
	<array>
		<dict>
			<key>match</key>
			<string>(--)</string>
			<key>name</key>
			<string>support.constant.custom-property-name.prefix.css</string>
		</dict>
		<dict>
			<key>match</key>
			<string>([_a-zA-Z]+[_a-zA-Z0-9-]*)</string>
			<key>name</key>
			<string>support.type.variable-name.css</string>
		</dict>
		<dict>
			<key>match</key>
			<string>(,)</string>
			<key>name</key>
			<string>punctuation.definition.arbitrary-repitition.css</string>
		</dict>
		<dict>
			<key>include</key>
			<string>#numeric-values</string>
		</dict>
	</array>
	<key>end</key>
	<string>(\))</string>
	<key>endCaptures</key>
	<dict>
		<key>1</key>
		<dict>
			<key>name</key>
			<string>punctuation.section.function.css</string>
		</dict>
	</dict>
	<key>name</key>
	<string>support.type.cascading-variable.css</string>
</dict>