<key>font-face</key>
<dict>
	<key>begin</key>
	<string>\s*((@)font-face)\s*(?=\{)</string>
	<key>beginCaptures</key>
	<dict>
		<key>1</key>
		<dict>
			<key>name</key>
			<string>keyword.control.at-rule.font-face.css</string>
		</dict>
		<key>2</key>
		<dict>
			<key>name</key>
			<string>punctuation.definition.keyword.css</string>
		</dict>
	</dict>
	<key>end</key>
	<string>\s*(\})</string>
	<key>endCaptures</key>
	<dict>
		<key>1</key>
		<dict>
			<key>name</key>
			<string>punctuation.section.property-list.css</string>
		</dict>
	</dict>
	<key>name</key>
	<string>meta.at-rule.font-face.css</string>
	<key>patterns</key>
	<array>
		<dict>
			<key>include</key>
			<string>#rule-list</string>
		</dict>
	</array>
</dict>